[
  {
    "importName": "EssetionalSvg3DcubeLinear",
    "exportName": "Svg3Dcube",
    "category": "Essetional",
    "rootFolder": "linear"
  },
  {
    "importName": "EssetionalSvg3FullLinear",
    "exportName": "Svg3Full",
    "category": "Essetional",
    "rootFolder": "linear"
  },
  {
    "importName": "EssetionalAddCircleLinear",
    "exportName": "AddCircle",
    "category": "Essetional",
    "rootFolder": "linear"
  },
  {
    "importName": "EssetionalAddSquareLinear",
    "exportName": "AddSquare",
    "category": "Essetional",
    "rootFolder": "linear"
  },
  {
    "importName": "EssetionalAddLinear",
    "exportName": "Add",
    "category": "Essetional",
    "rootFolder": "linear"
  },
  {
    "importName": "EssetionalArchiveLinear",
    "exportName": "Archive",
    "category": "Essetional",
    "rootFolder": "linear"
  },
  {
    "importName": "EssetionalAutobrightnessLinear",
    "exportName": "Autobrightness",
    "category": "Essetional",
    "rootFolder": "linear"
  },
  {
    "importName": "EssetionalBatteryChargingLinear",
    "exportName": "BatteryCharging",
    "category": "Essetional",
    "rootFolder": "linear"
  },
  {
    "importName": "EssetionalBatteryDisableLinear",
    "exportName": "BatteryDisable",
    "category": "Essetional",
    "rootFolder": "linear"
  },
  {
    "importName": "EssetionalBatteryEmpty1Linear",
    "exportName": "BatteryEmpty1",
    "category": "Essetional",
    "rootFolder": "linear"
  },
  {
    "importName": "EssetionalBatteryEmptyLinear",
    "exportName": "BatteryEmpty",
    "category": "Essetional",
    "rootFolder": "linear"
  },
  {
    "importName": "EssetionalBatteryFullLinear",
    "exportName": "BatteryFull",
    "category": "Essetional",
    "rootFolder": "linear"
  },
  {
    "importName": "EssetionalBox2Linear",
    "exportName": "Box2",
    "category": "Essetional",
    "rootFolder": "linear"
  },
  {
    "importName": "EssetionalBroomLinear",
    "exportName": "Broom",
    "category": "Essetional",
    "rootFolder": "linear"
  },
  {
    "importName": "EssetionalBubbleLinear",
    "exportName": "Bubble",
    "category": "Essetional",
    "rootFolder": "linear"
  },
  {
    "importName": "EssetionalCakeLinear",
    "exportName": "Cake",
    "category": "Essetional",
    "rootFolder": "linear"
  },
  {
    "importName": "EssetionalCdLinear",
    "exportName": "Cd",
    "category": "Essetional",
    "rootFolder": "linear"
  },
  {
    "importName": "EssetionalChartLinear",
    "exportName": "Chart",
    "category": "Essetional",
    "rootFolder": "linear"
  },
  {
    "importName": "EssetionalChromeLinear",
    "exportName": "Chrome",
    "category": "Essetional",
    "rootFolder": "linear"
  },
  {
    "importName": "EssetionalCloseCircleLinear",
    "exportName": "CloseCircle",
    "category": "Essetional",
    "rootFolder": "linear"
  },
  {
    "importName": "EssetionalCloseSquareLinear",
    "exportName": "CloseSquare",
    "category": "Essetional",
    "rootFolder": "linear"
  },
  {
    "importName": "EssetionalCoffeeLinear",
    "exportName": "Coffee",
    "category": "Essetional",
    "rootFolder": "linear"
  },
  {
    "importName": "EssetionalComputingLinear",
    "exportName": "Computing",
    "category": "Essetional",
    "rootFolder": "linear"
  },
  {
    "importName": "EssetionalCrown1Linear",
    "exportName": "Crown1",
    "category": "Essetional",
    "rootFolder": "linear"
  },
  {
    "importName": "EssetionalCrownLinear",
    "exportName": "Crown",
    "category": "Essetional",
    "rootFolder": "linear"
  },
  {
    "importName": "EssetionalCupLinear",
    "exportName": "Cup",
    "category": "Essetional",
    "rootFolder": "linear"
  },
  {
    "importName": "EssetionalDangerLinear",
    "exportName": "Danger",
    "category": "Essetional",
    "rootFolder": "linear"
  },
  {
    "importName": "EssetionalDiamondsLinear",
    "exportName": "Diamonds",
    "category": "Essetional",
    "rootFolder": "linear"
  },
  {
    "importName": "EssetionalDiscoverLinear",
    "exportName": "Discover",
    "category": "Essetional",
    "rootFolder": "linear"
  },
  {
    "importName": "EssetionalEmojiHappyLinear",
    "exportName": "EmojiHappy",
    "category": "Essetional",
    "rootFolder": "linear"
  },
  {
    "importName": "EssetionalEmojiNormalLinear",
    "exportName": "EmojiNormal",
    "category": "Essetional",
    "rootFolder": "linear"
  },
  {
    "importName": "EssetionalEmojiSadLinear",
    "exportName": "EmojiSad",
    "category": "Essetional",
    "rootFolder": "linear"
  },
  {
    "importName": "EssetionalFilterAddLinear",
    "exportName": "FilterAdd",
    "category": "Essetional",
    "rootFolder": "linear"
  },
  {
    "importName": "EssetionalFilterEditLinear",
    "exportName": "FilterEdit",
    "category": "Essetional",
    "rootFolder": "linear"
  },
  {
    "importName": "EssetionalFilterRemoveLinear",
    "exportName": "FilterRemove",
    "category": "Essetional",
    "rootFolder": "linear"
  },
  {
    "importName": "EssetionalFilterSearchLinear",
    "exportName": "FilterSearch",
    "category": "Essetional",
    "rootFolder": "linear"
  },
  {
    "importName": "EssetionalFilterSquareLinear",
    "exportName": "FilterSquare",
    "category": "Essetional",
    "rootFolder": "linear"
  },
  {
    "importName": "EssetionalFilterTickLinear",
    "exportName": "FilterTick",
    "category": "Essetional",
    "rootFolder": "linear"
  },
  {
    "importName": "EssetionalFilterLinear",
    "exportName": "Filter",
    "category": "Essetional",
    "rootFolder": "linear"
  },
  {
    "importName": "EssetionalFlag2Linear",
    "exportName": "Flag2",
    "category": "Essetional",
    "rootFolder": "linear"
  },
  {
    "importName": "EssetionalFlagLinear",
    "exportName": "Flag",
    "category": "Essetional",
    "rootFolder": "linear"
  },
  {
    "importName": "EssetionalFlashCircleLinear",
    "exportName": "FlashCircle",
    "category": "Essetional",
    "rootFolder": "linear"
  },
  {
    "importName": "EssetionalFlashSlashLinear",
    "exportName": "FlashSlash",
    "category": "Essetional",
    "rootFolder": "linear"
  },
  {
    "importName": "EssetionalFlashLinear",
    "exportName": "Flash",
    "category": "Essetional",
    "rootFolder": "linear"
  },
  {
    "importName": "EssetionalGhostLinear",
    "exportName": "Ghost",
    "category": "Essetional",
    "rootFolder": "linear"
  },
  {
    "importName": "EssetionalGlassLinear",
    "exportName": "Glass",
    "category": "Essetional",
    "rootFolder": "linear"
  },
  {
    "importName": "EssetionalGrammerlyLinear",
    "exportName": "Grammerly",
    "category": "Essetional",
    "rootFolder": "linear"
  },
  {
    "importName": "EssetionalGroup1Linear",
    "exportName": "Group1",
    "category": "Essetional",
    "rootFolder": "linear"
  },
  {
    "importName": "EssetionalGroup2Linear",
    "exportName": "Group2",
    "category": "Essetional",
    "rootFolder": "linear"
  },
  {
    "importName": "EssetionalGroupLinear",
    "exportName": "Group",
    "category": "Essetional",
    "rootFolder": "linear"
  },
  {
    "importName": "EssetionalHappyemojiLinear",
    "exportName": "Happyemoji",
    "category": "Essetional",
    "rootFolder": "linear"
  },
  {
    "importName": "EssetionalHome2Linear",
    "exportName": "Home2",
    "category": "Essetional",
    "rootFolder": "linear"
  },
  {
    "importName": "EssetionalHomeWifiLinear",
    "exportName": "HomeWifi",
    "category": "Essetional",
    "rootFolder": "linear"
  },
  {
    "importName": "EssetionalHomeLinear",
    "exportName": "Home",
    "category": "Essetional",
    "rootFolder": "linear"
  },
  {
    "importName": "EssetionalInfoCircleLinear",
    "exportName": "InfoCircle",
    "category": "Essetional",
    "rootFolder": "linear"
  },
  {
    "importName": "EssetionalInformationLinear",
    "exportName": "Information",
    "category": "Essetional",
    "rootFolder": "linear"
  },
  {
    "importName": "EssetionalInstagramLinear",
    "exportName": "Instagram",
    "category": "Essetional",
    "rootFolder": "linear"
  },
  {
    "importName": "EssetionalJudgeLinear",
    "exportName": "Judge",
    "category": "Essetional",
    "rootFolder": "linear"
  },
  {
    "importName": "EssetionalLampLinear",
    "exportName": "Lamp",
    "category": "Essetional",
    "rootFolder": "linear"
  },
  {
    "importName": "EssetionalLevelLinear",
    "exportName": "Level",
    "category": "Essetional",
    "rootFolder": "linear"
  },
  {
    "importName": "EssetionalMenuLinear",
    "exportName": "Menu",
    "category": "Essetional",
    "rootFolder": "linear"
  },
  {
    "importName": "EssetionalMilkLinear",
    "exportName": "Milk",
    "category": "Essetional",
    "rootFolder": "linear"
  },
  {
    "importName": "EssetionalMinusCirlceLinear",
    "exportName": "MinusCirlce",
    "category": "Essetional",
    "rootFolder": "linear"
  },
  {
    "importName": "EssetionalMinusSquareLinear",
    "exportName": "MinusSquare",
    "category": "Essetional",
    "rootFolder": "linear"
  },
  {
    "importName": "EssetionalMinusLinear",
    "exportName": "Minus",
    "category": "Essetional",
    "rootFolder": "linear"
  },
  {
    "importName": "EssetionalMirrorLinear",
    "exportName": "Mirror",
    "category": "Essetional",
    "rootFolder": "linear"
  },
  {
    "importName": "EssetionalMoreCircleLinear",
    "exportName": "MoreCircle",
    "category": "Essetional",
    "rootFolder": "linear"
  },
  {
    "importName": "EssetionalMoreSquareLinear",
    "exportName": "MoreSquare",
    "category": "Essetional",
    "rootFolder": "linear"
  },
  {
    "importName": "EssetionalMouseCircleLinear",
    "exportName": "MouseCircle",
    "category": "Essetional",
    "rootFolder": "linear"
  },
  {
    "importName": "EssetionalMouseSquareLinear",
    "exportName": "MouseSquare",
    "category": "Essetional",
    "rootFolder": "linear"
  },
  {
    "importName": "EssetionalMouseLinear",
    "exportName": "Mouse",
    "category": "Essetional",
    "rootFolder": "linear"
  },
  {
    "importName": "EssetionalPetLinear",
    "exportName": "Pet",
    "category": "Essetional",
    "rootFolder": "linear"
  },
  {
    "importName": "EssetionalRankingLinear",
    "exportName": "Ranking",
    "category": "Essetional",
    "rootFolder": "linear"
  },
  {
    "importName": "EssetionalReserveLinear",
    "exportName": "Reserve",
    "category": "Essetional",
    "rootFolder": "linear"
  },
  {
    "importName": "EssetionalSafeHomeLinear",
    "exportName": "SafeHome",
    "category": "Essetional",
    "rootFolder": "linear"
  },
  {
    "importName": "EssetionalSend2Linear",
    "exportName": "Send2",
    "category": "Essetional",
    "rootFolder": "linear"
  },
  {
    "importName": "EssetionalSendLinear",
    "exportName": "Send",
    "category": "Essetional",
    "rootFolder": "linear"
  },
  {
    "importName": "EssetionalShareLinear",
    "exportName": "Share",
    "category": "Essetional",
    "rootFolder": "linear"
  },
  {
    "importName": "EssetionalSignpostLinear",
    "exportName": "Signpost",
    "category": "Essetional",
    "rootFolder": "linear"
  },
  {
    "importName": "EssetionalSlashLinear",
    "exportName": "Slash",
    "category": "Essetional",
    "rootFolder": "linear"
  },
  {
    "importName": "EssetionalSliderLinear",
    "exportName": "Slider",
    "category": "Essetional",
    "rootFolder": "linear"
  },
  {
    "importName": "EssetionalSmartHomeLinear",
    "exportName": "SmartHome",
    "category": "Essetional",
    "rootFolder": "linear"
  },
  {
    "importName": "EssetionalSortLinear",
    "exportName": "Sort",
    "category": "Essetional",
    "rootFolder": "linear"
  },
  {
    "importName": "EssetionalSoundLinear",
    "exportName": "Sound",
    "category": "Essetional",
    "rootFolder": "linear"
  },
  {
    "importName": "EssetionalSpeedometerLinear",
    "exportName": "Speedometer",
    "category": "Essetional",
    "rootFolder": "linear"
  },
  {
    "importName": "EssetionalStatusLinear",
    "exportName": "Status",
    "category": "Essetional",
    "rootFolder": "linear"
  },
  {
    "importName": "EssetionalStickerLinear",
    "exportName": "Sticker",
    "category": "Essetional",
    "rootFolder": "linear"
  },
  {
    "importName": "EssetionalStoryLinear",
    "exportName": "Story",
    "category": "Essetional",
    "rootFolder": "linear"
  },
  {
    "importName": "EssetionalTagCrossLinear",
    "exportName": "TagCross",
    "category": "Essetional",
    "rootFolder": "linear"
  },
  {
    "importName": "EssetionalTagRightLinear",
    "exportName": "TagRight",
    "category": "Essetional",
    "rootFolder": "linear"
  },
  {
    "importName": "EssetionalTickCircleLinear",
    "exportName": "TickCircle",
    "category": "Essetional",
    "rootFolder": "linear"
  },
  {
    "importName": "EssetionalTickSquareLinear",
    "exportName": "TickSquare",
    "category": "Essetional",
    "rootFolder": "linear"
  },
  {
    "importName": "EssetionalTrashLinear",
    "exportName": "Trash",
    "category": "Essetional",
    "rootFolder": "linear"
  },
  {
    "importName": "EssetionalTreeLinear",
    "exportName": "Tree",
    "category": "Essetional",
    "rootFolder": "linear"
  },
  {
    "importName": "EssetionalTriangleLinear",
    "exportName": "Triangle",
    "category": "Essetional",
    "rootFolder": "linear"
  },
  {
    "importName": "EssetionalTrushSquareLinear",
    "exportName": "TrushSquare",
    "category": "Essetional",
    "rootFolder": "linear"
  },
  {
    "importName": "EssetionalVerifyLinear",
    "exportName": "Verify",
    "category": "Essetional",
    "rootFolder": "linear"
  },
  {
    "importName": "EssetionalWarning2Linear",
    "exportName": "Warning2",
    "category": "Essetional",
    "rootFolder": "linear"
  },
  {
    "importName": "EssetionalWeightLinear",
    "exportName": "Weight",
    "category": "Essetional",
    "rootFolder": "linear"
  },
  {
    "importName": "EssetionalWifiSquareLinear",
    "exportName": "WifiSquare",
    "category": "Essetional",
    "rootFolder": "linear"
  },
  {
    "importName": "EssetionalWifiLinear",
    "exportName": "Wifi",
    "category": "Essetional",
    "rootFolder": "linear"
  }
]
